dukto/Process.py
dukto/__init__.py
dukto/base_processor.py
dukto/cus_types.py
dukto/logger.py
dukto/pipe.py
dukto/processor.py
dukto/utils.py
dukto-0.1.8.dist-info/LICENSE
dukto-0.1.8.dist-info/METADATA
dukto-0.1.8.dist-info/WHEEL
dukto-0.1.8.dist-info/top_level.txt
dukto-0.1.8.dist-info/RECORD
